{
  "parent": "minecraft:recipes/root",
  "rewards": {
    "recipes": [
      "assembledblocks:dis_quadruple_assembled_stone"
    ]
  },
  "criteria": {
    "unlock": {
      "trigger": "minecraft:inventory_changed",
      "conditions": {
        "items": [
          {
            "items": [
              "assembledblocks:1_0_stone/duodecuple_assembled_stone"
            ]
          }
        ]
      }
    },
    "has_the_recipe": {
      "trigger": "minecraft:recipe_unlocked",
      "conditions": {
        "recipe": "assembledblocks:dis_quadruple_assembled_stone"
      }
    }
  },
  "requirements": [
    [
      "unlock",
      "has_the_recipe"
    ]
  ]
}